<crs>
	<Name>CO</Name>
	<Collider>ph</Collider>
	
	<title> CO + $\lambda \rightarrow$ O(${^{1}}$D) + C</title>
	<Emin>13</Emin>
	<Emax>10000</Emax>
	<Cmax>5E-17</Cmax>
	<Cmin>1E-23</Cmin>
	<plotname>seff_CO_ph_O1D.pdf</plotname>
	<lambplotname>seff_CO_ph_O1D_lambda.pdf</lambplotname>
	
	
	<CO>

		<Process name="CO + hv -> C(1D) + O(1D)" electrons="0" threshold="14.36">
			<Species>
				<Specie name="C" state="1D"/>
				<Specie name="O" state="1D"/>
			</Species>

			<legend>O($^1$D) + C($^1$D) (PHIDRATES + McElroy)</legend>
			<Proc>O($^1$D) + C($^1$D)</Proc>
			<Section>excitation</Section> <!-- total | elastic | ionization | dissociation | excitation | emission -->
			<Source type="adaptation"> PHIDRATES + McElroy </Source> <!-- types : measurement, bratio, theory, review, adaptation, unknown -->
			<Notes>Adapted nm -> eV, website.  \cite{Huebner2015}. Adaptation from a Branching ratio in McElroy and McConnel (1971) \cite{Mcelroy1971}: We estimate the uncertainty at 50%</Notes>
			<EstimatedUncertainty/>
			<Extrapolated/>
			<Egrid unit="eV">
				14.358332	     14.366651	     14.396679	     14.413415	     14.416767
				14.433551	     14.445322	     14.450373	     14.463859	     14.480752
				14.514657	     14.524859	     14.540190	     14.547014	     14.553844
				14.569236	     14.603557	     14.612163	     14.620778	     14.641497
				14.650148	     14.660542	     14.672686	     14.690071	     14.707497
				14.738968	     14.760024	     14.786428	     14.827099	     14.844852
				14.857304	     14.871561	     14.875129	     14.894786	     14.923471
				14.939655	     14.955875	     14.977555	     14.992044	     15.002928
				15.021105	     15.037502	     15.064909	     15.092416	     15.101608
				15.123713	     15.147734	     15.156993	     15.175545	     15.186698
				15.223993	     15.250209	     15.287818	     15.302913	     15.335090
				15.361690	     15.378839	     15.396026	     15.407506	     15.440125
				15.484476	     15.503839	     15.517422	     15.536867	     15.550508
				15.560266	     15.575905	     15.583736	     15.593535	     15.615139
				15.630888	     15.664460	     15.682292	     15.690230	     15.714094
				15.740028	     15.772065	     15.794166	     15.806247	     15.838554
				15.852730	     15.860842	     15.885227	     15.895410	     15.905606
				15.936272	     15.969114	     15.993834	     16.006223	     16.008289
				16.014492	     16.031058	     16.037278	     16.049735	     16.068455
				16.078874	     16.101844	     16.147981	     16.154293	     16.164824
				16.175369	     16.204967	     16.219806	     16.226175	     16.232548
				16.243181	     16.249567	     16.270892	     16.290133	     16.298699
				16.305129	     16.307273	     16.326600	     16.335204	     16.341663
				16.345972	     16.374036	     16.397857	     16.417399	     16.432631
				16.465365	     16.487261	     16.504819	     16.533431	     16.542255
				16.548879	     16.568783	     16.593175	     16.615411	     16.637708
				16.653351	     16.720728	     16.745570	     16.765950	     16.793201
				16.815977	     16.891580	     16.910011	     16.926171	     16.937732
				16.979485	     16.995778	     17.042502	     17.054223	     17.080066
				17.124890	     17.148575	     17.196144	     17.243978	     17.292078
				17.304145	     17.376903	     17.413511	     17.462563	     17.511893
				17.549073	     17.586411	     17.712029	     17.903856	     17.942721
				18.047191	     18.160861	     18.206197	     18.232971	     18.340858
				18.368030	     18.444540	     18.491305	     18.560509	     18.652655
				18.680759	     18.785485	     18.848313	     18.900030	     18.928885
				18.946241	     18.972334	     19.074492	     19.148139	     19.204492
				19.282146	     19.300156	     19.336276	     19.402848	     19.418042
				19.680032	     19.689408	     19.774195	     19.808947	     19.834299
				19.850176	     19.997452	     20.094684	     20.160033	     20.298657
				20.325279	     20.378731	     20.664033	     20.677819	     20.740080
				21.014271	     21.219271	     21.963543	     22.199499	     22.319388
				22.485346	     22.587757	     22.761924	     23.023993	     23.548756
				23.870658	     24.121440	     24.382340	     24.786925	     25.001855
				25.215416	     25.479696	     25.862370	     26.085462	     26.295695
				26.640352	     26.836407	     26.994165	     27.100372	     27.570425
				27.736957	     28.038037	     28.391161	     29.811060	     30.240049
				30.583177	     31.790821	     32.507656	     33.088924	     34.155427
				35.282925	     36.757842	     37.685167	     40.306957	     41.647363
				43.079986	     44.614682	     46.262761	     48.055891	     49.953344
				52.028619	     54.283800	     56.769322	     59.464844	     62.429104
				65.704399	     69.342394	     73.406868	     77.977484	     83.099330
				89.069109	     95.963003	    103.926404	    113.331079	    124.607236
				138.375223	    171.012690	    240.746019	    344.400556	    460.907807
				652.548421	    991.873600	   1653.122667	   3099.605000	   6199.210000
				12398.420000
			</Egrid>
			<Cross unit="cm2" uncertainty="50%">
				0.000000e+00	  3.050000e-20	  3.430000e-20	  5.140000e-20	  1.010000e-19
				7.440000e-20	  1.000000e-19	  8.360000e-20	  1.350000e-19	  1.040000e-19
				1.630000e-19	  1.520000e-19	  1.540000e-19	  1.570000e-19	  1.570000e-19
				1.990000e-19	  1.910000e-19	  2.090000e-19	  2.500000e-19	  1.520000e-19
				1.760000e-19	  1.940000e-19	  1.930000e-19	  2.440000e-19	  1.490000e-19
				1.880000e-19	  8.040000e-20	  2.860000e-19	  4.730000e-19	  3.720000e-19
				3.800000e-19	  3.620000e-19	  4.000000e-19	  5.620000e-19	  5.130000e-19
				6.570000e-19	  5.810000e-19	  1.310000e-18	  1.790000e-18	  2.210000e-18
				2.040000e-18	  3.300000e-18	  9.660000e-19	  4.150000e-18	  3.330000e-18
				4.300000e-18	  7.860000e-18	  1.680000e-17	  6.890000e-18	  5.030000e-18
				1.380000e-17	  1.180000e-18	  7.150000e-18	  4.900000e-18	  7.900000e-18
				3.020000e-17	  1.050000e-17	  1.000000e-17	  6.960000e-18	  2.850000e-18
				8.750000e-18	  5.910000e-18	  6.950000e-18	  2.800000e-17	  2.310000e-17
				1.940000e-17	  5.520000e-18	  5.160000e-18	  3.640000e-18	  8.980000e-18
				5.760000e-18	  1.880000e-17	  8.470000e-18	  5.110000e-18	  3.120000e-17
				5.150000e-18	  3.830000e-18	  9.390000e-18	  8.350000e-18	  2.340000e-17
				2.330000e-17	  2.120000e-17	  5.780000e-18	  1.290000e-17	  9.670000e-18
				3.530000e-18	  6.120000e-18	  1.990000e-17	  1.640000e-17	  1.110000e-17
				1.250000e-17	  1.640000e-17	  1.430000e-17	  1.940000e-17	  6.500000e-18
				9.690000e-18	  3.900000e-18	  1.450000e-17	  1.540000e-17	  1.660000e-17
				1.600000e-17	  1.000000e-17	  2.030000e-17	  2.660000e-17	  2.400000e-17
				7.490000e-18	  1.510000e-17	  5.980000e-18	  3.490000e-18	  7.990000e-18
				6.120000e-18	  7.070000e-18	  9.420000e-18	  1.400000e-17	  9.870000e-18
				1.660000e-17	  1.950000e-17	  1.670000e-17	  1.810000e-17	  8.780000e-18
				1.170000e-17	  8.920000e-18	  1.040000e-17	  1.470000e-17	  1.540000e-17
				1.730000e-17	  1.040000e-17	  1.670000e-17	  9.110000e-18	  1.040000e-17
				9.700000e-18	  1.790000e-17	  8.770000e-18	  1.040000e-17	  9.120000e-18
				1.000000e-17	  1.430000e-17	  1.580000e-17	  1.280000e-17	  1.280000e-17
				7.430000e-18	  1.060000e-17	  1.340000e-17	  1.210000e-17	  1.810000e-17
				1.320000e-17	  1.080000e-17	  1.150000e-17	  5.970000e-18	  4.820000e-18
				9.120000e-18	  5.970000e-18	  8.580000e-18	  6.120000e-18	  5.780000e-18
				4.470000e-18	  7.820000e-18	  7.630000e-18	  4.830000e-18	  8.910000e-18
				5.390000e-18	  1.380000e-17	  1.490000e-17	  3.370000e-18	  2.230000e-18
				7.430000e-18	  1.810000e-17	  1.660000e-17	  4.100000e-18	  7.990000e-18
				9.290000e-18	  1.670000e-18	  7.440000e-18	  2.980000e-18	  2.970000e-18
				1.040000e-17	  6.320000e-18	  1.670000e-18	  6.700000e-18	  8.750000e-18
				1.130000e-18	  4.470000e-18	  8.150000e-18	  7.820000e-18	  6.310000e-18
				1.860000e-18	  3.980000e-19	  3.060000e-19	  3.980000e-19	  4.970000e-19
				4.990000e-19	  1.290000e-18	  7.040000e-19	  7.500000e-19	  1.560000e-18
				1.670000e-18	  4.990000e-19	  1.670000e-18	  7.100000e-19	  6.930000e-19
				5.810000e-19	  7.460000e-19	  0.000000e+00	  0.000000e+00	  0.000000e+00
				0.000000e+00	  0.000000e+00	  1.080000e-19	  0.000000e+00	  8.520000e-20
				0.000000e+00	  0.000000e+00	  8.400000e-20	  0.000000e+00	  0.000000e+00
				0.000000e+00	  0.000000e+00	  0.000000e+00	  0.000000e+00	  4.120000e-20
				0.000000e+00	  8.080000e-20	  0.000000e+00	  6.000000e-20	  5.880000e-20
				7.760000e-20	  7.680000e-20	  1.880000e-20	  3.460000e-20	  6.720000e-20
				1.650000e-21	  0.000000e+00	  8.940000e-20	  2.920000e-20	  2.800000e-20
				0.000000e+00	  5.280000e-20	  0.000000e+00	  0.000000e+00	  0.000000e+00
				0.000000e+00	  0.000000e+00	  0.000000e+00	  0.000000e+00	  0.000000e+00
				0.000000e+00	  0.000000e+00	  0.000000e+00	  0.000000e+00	  0.000000e+00
				0.000000e+00	  4.960000e-20	  4.420000e-20	  3.880000e-20	  6.900000e-20
				3.000000e-20	  7.740000e-20	  4.360000e-20	  3.560000e-20	  4.290000e-20
				4.400000e-20	  1.290000e-20	  4.560000e-21	  1.110000e-21	  1.170000e-20
				3.250000e-21	  1.040000e-21	  1.470000e-22	  9.480000e-24	  9.030000e-25
				0.000000e+00
			</Cross>
		</Process>

	</CO>
</crs>
